envlight/__init__.py
envlight/light.py
envlight/utils.py
envlight/renderutils/__init__.py
envlight/renderutils/bsdf.py
envlight/renderutils/loss.py
envlight/renderutils/ops.py
envlight/renderutils/c_src/bsdf.cu
envlight/renderutils/c_src/bsdf.h
envlight/renderutils/c_src/common.cpp
envlight/renderutils/c_src/common.h
envlight/renderutils/c_src/cubemap.cu
envlight/renderutils/c_src/cubemap.h
envlight/renderutils/c_src/loss.cu
envlight/renderutils/c_src/loss.h
envlight/renderutils/c_src/mesh.cu
envlight/renderutils/c_src/mesh.h
envlight/renderutils/c_src/normal.cu
envlight/renderutils/c_src/normal.h
envlight/renderutils/c_src/tensor.h
envlight/renderutils/c_src/torch_bindings.cpp
envlight/renderutils/c_src/vec3f.h
envlight/renderutils/c_src/vec4f.h
envlight-0.1.0.dist-info/LICENSE
envlight-0.1.0.dist-info/LICENSE_NVIDIA
envlight-0.1.0.dist-info/METADATA
envlight-0.1.0.dist-info/WHEEL
envlight-0.1.0.dist-info/top_level.txt
envlight-0.1.0.dist-info/RECORD
